cloudregister/__init__.py
cloudregister/__main__.py
cloudregister/cloudregister.py
keywind_cloudregister-0.0.3.dist-info/LICENSE
keywind_cloudregister-0.0.3.dist-info/METADATA
keywind_cloudregister-0.0.3.dist-info/WHEEL
keywind_cloudregister-0.0.3.dist-info/top_level.txt
keywind_cloudregister-0.0.3.dist-info/RECORD
